djangoldp_indexing/__init__.py
djangoldp_indexing/apps.py
djangoldp_indexing/djangoldp_urls.py
djangoldp_indexing/middleware.py
djangoldp_indexing/management/__init__.py
djangoldp_indexing/management/commands/__init__.py
djangoldp_indexing/management/commands/crawl_indexes.py
djangoldp_indexing/management/commands/crawl_indexes_initial.py
djangoldp_indexing/management/commands/crawl_indexes_recursive.py
djangoldp_indexing/management/commands/generate_local_indexes.py
djangoldp_indexing/tests/__init__.py
djangoldp_indexing/tests/base.py
djangoldp_indexing/tests/models.py
djangoldp_indexing/tests/runner.py
djangoldp_indexing/tests/test_policy_enforcement.py
djangoldp_indexing/tests/urls.py
djangoldp_indexing/tests/test_instance/__init__.py
djangoldp_indexing/tests/test_instance/test_indexes_root.py
djangoldp_indexing/tests/test_model/__init__.py
djangoldp_indexing/tests/test_model/test_pattern_index.py
djangoldp_indexing/tests/test_model/test_property_index.py
djangoldp_indexing/tests/test_model/test_root_index.py
djangoldp_indexing/views/__init__.py
djangoldp_indexing/views/base.py
djangoldp_indexing/views/static.py
djangoldp_indexing/views/instance/__init__.py
djangoldp_indexing/views/instance/indexes.py
djangoldp_indexing/views/instance/root.py
djangoldp_indexing/views/instance/type_index.py
djangoldp_indexing/views/instance/webid.py
djangoldp_indexing/views/model/__init__.py
djangoldp_indexing/views/model/pattern.py
djangoldp_indexing/views/model/property.py
djangoldp_indexing/views/model/root.py
djangoldp_indexing-2.0.1.dist-info/licenses/LICENSE
djangoldp_indexing-2.0.1.dist-info/METADATA
djangoldp_indexing-2.0.1.dist-info/WHEEL
djangoldp_indexing-2.0.1.dist-info/top_level.txt
djangoldp_indexing-2.0.1.dist-info/RECORD
