Metadata-Version: 2.4
Name: djangoldp-indexing
Version: 2.0.1
Summary: DjangoLDP extension for model indexing and pattern-based search
Home-page: https://git.startinblox.com/djangoldp-packages/djangoldp-indexing
Author: Startin'blox
Author-email: tech@startinblox.com
License: MIT
Classifier: Development Status :: 4 - Beta
Classifier: Environment :: Web Environment
Classifier: Framework :: Django
Classifier: Framework :: Django :: 5.2
Classifier: Intended Audience :: Developers
Classifier: License :: OSI Approved :: MIT License
Classifier: Operating System :: OS Independent
Classifier: Programming Language :: Python
Classifier: Programming Language :: Python :: 3
Classifier: Programming Language :: Python :: 3.8
Classifier: Programming Language :: Python :: 3.9
Classifier: Programming Language :: Python :: 3.10
Classifier: Programming Language :: Python :: 3.11
Classifier: Topic :: Internet :: WWW/HTTP
Classifier: Topic :: Software Development :: Libraries :: Python Modules
Requires-Python: >=3.8
License-File: LICENSE
Requires-Dist: Django>=5.2
Requires-Dist: djangorestframework>=3.12.0
Requires-Dist: djangoldp~=5.0.0
Requires-Dist: djangoldp_edc~=1.0.0
Requires-Dist: pyld~=1.0.0
Provides-Extra: dev
Requires-Dist: pytest; extra == "dev"
Requires-Dist: pytest-django; extra == "dev"
Requires-Dist: factory_boy; extra == "dev"
Dynamic: license-file
